tests/__init__.py
tests/test_cff.py
cffsdk-0.1.1.dist-info/LICENSE
cffsdk-0.1.1.dist-info/METADATA
cffsdk-0.1.1.dist-info/WHEEL
cffsdk-0.1.1.dist-info/top_level.txt
cffsdk-0.1.1.dist-info/RECORD
