Metadata-Version: 2.1
Name: cffsdk
Version: 0.1.1
Summary: A Python client for interacting with CFF server.
Home-page: https://github.com/atripathy86/cff
Author: Aalap Tripathy
Author-email: aalap.tripathy@hpe.com
Classifier: Programming Language :: Python :: 3
Classifier: License :: OSI Approved :: MIT License
Classifier: Operating System :: OS Independent
Requires-Python: >=3.7
License-File: LICENSE
Requires-Dist: requests >=2.0.0
